suntranslator.py
config/config
data/fonts/SUN7_8_1210.ttf
data/fonts/sun7_8_1210.kmp
data/symbols/sun_dictionary.csv
gui/__init__.py
gui/app.py
gui/menubar.py
gui/views/__init__.py
gui/views/translator_view.py
translator/__init__.py
translator/translate.py
suntranslator-0.0.9.post1.dist-info/LICENSE.txt
suntranslator-0.0.9.post1.dist-info/METADATA
suntranslator-0.0.9.post1.dist-info/WHEEL
suntranslator-0.0.9.post1.dist-info/entry_points.txt
suntranslator-0.0.9.post1.dist-info/top_level.txt
suntranslator-0.0.9.post1.dist-info/RECORD
