Metadata-Version: 2.1
Name: suntranslator
Version: 0.0.9.post1
Summary: A program to convert text into the Sun language
Author-email: Carl Head <chead@linuxmail.org>
Project-URL: Homepage, https://github.com/cjhead/suntranslator
Classifier: Programming Language :: Python :: 3.10
Classifier: License :: OSI Approved :: GNU General Public License v3 (GPLv3)
Classifier: Operating System :: OS Independent
Requires-Python: >=3.10
License-File: LICENSE.txt
Requires-Dist: fpdf2
